{
  "code": 0
  ,"msg": ""
  ,"count": 5
  ,"data": [{
    "id": "1"
    ,"hospital": "人民医院"
    ,"productA1": "66,667"
    ,"productA2": "66,667"
    ,"productA3": "66,667"
    ,"productB1": "13,333"
    ,"productB2": "13,333"
    ,"productB3": "13,333"
    ,"productC1": "代表1"
    ,"productC2": "代表1"
    ,"productC3": "代表1"
  },{
    "id": "2"
    ,"hospital": "协和医院"
    ,"productA1": "66,667"
    ,"productA2": "66,667"
    ,"productA3": "66,667"
    ,"productB1": "13,333"
    ,"productB2": "13,333"
    ,"productB3": "13,333"
    ,"productC1": "代表1"
    ,"productC2": "代表1"
    ,"productC3": "代表1"
  },{
    "id": "3"
    ,"hospital": "肿瘤医院"
    ,"productA1": "66,667"
    ,"productA2": "66,667"
    ,"productA3": "66,667"
    ,"productB1": "13,333"
    ,"productB2": "13,333"
    ,"productB3": "13,333"
    ,"productC1": "代表2"
    ,"productC2": "代表2"
    ,"productC3": "代表2"
},{
    "id": "4"
    ,"hospital": "妇产医院"
    ,"productA1": "66,667"
    ,"productA2": "66,667"
    ,"productA3": "66,667"
    ,"productB1": "13,333"
    ,"productB2": "13,333"
    ,"productB3": "13,333"
    ,"productC1": "代表3"
    ,"productC2": "代表3"
    ,"productC3": "代表3"
},{
    "id": "5"
    ,"hospital": "社区医院"
    ,"productA1": "66,667"
    ,"productA2": "66,667"
    ,"productA3": "66,667"
    ,"productB1": "13,333"
    ,"productB2": "13,333"
    ,"productB3": "13,333"
    ,"productC1": "代表3"
    ,"productC2": "代表3"
    ,"productC3": "代表3"
  }]
}